{
  "directTimers": [
    [
      1652659203000, 
      36
    ]
  ], 
  "GyverStepper": [
    [
      1652659203000, 
      547
    ]
  ], 
  "PWMrelay": [
    [
      1652659203000, 
      65
    ]
  ], 
  "GyverEncoder": [
    [
      1652659203000, 
      121
    ]
  ], 
  "CRT": [
    [
      1652659203000, 
      12
    ]
  ], 
  "GyverPortal": [
    [
      1652659203000, 
      1355
    ]
  ], 
  "GyverHC595": [
    [
      1652659203000, 
      127
    ]
  ], 
  "UnixTime": [
    [
      1652659203000, 
      187
    ]
  ], 
  "ServoSmooth": [
    [
      1652659203000, 
      159
    ]
  ], 
  "GyverINA": [
    [
      1652659203000, 
      170
    ]
  ], 
  "Psychrometer": [
    [
      1652659203000, 
      25
    ]
  ], 
  "GyverMAX7219": [
    [
      1652659203000, 
      204
    ]
  ], 
  "GyverWDT": [
    [
      1652659203000, 
      55
    ]
  ], 
  "GyverBus": [
    [
      1652659203000, 
      115
    ]
  ], 
  "Tachometer": [
    [
      1652659203000, 
      142
    ]
  ], 
  "TimeRandom": [
    [
      1652659203000, 
      19
    ]
  ], 
  "GyverTM1637": [
    [
      1652659203000, 
      348
    ]
  ], 
  "AnalogKey": [
    [
      1652659203000, 
      89
    ]
  ], 
  "VolAnalyzer": [
    [
      1652659203000, 
      147
    ]
  ], 
  "microDS3231": [
    [
      1652659203000, 
      289
    ]
  ], 
  "EasyHID": [
    [
      1652659203000, 
      360
    ]
  ], 
  "GyverJoy": [
    [
      1652659203000, 
      58
    ]
  ], 
  "Random16": [
    [
      1652659203000, 
      50
    ]
  ], 
  "SevenSegmentsDisp": [
    [
      1652659203000, 
      91
    ]
  ], 
  "GyverFIFO": [
    [
      1652659203000, 
      29
    ]
  ], 
  "AlexGyver": [], 
  "GyverNTP": [
    [
      1652659203000, 
      231
    ]
  ], 
  "ProcessingPlotter": [
    [
      1652659203000, 
      25
    ]
  ], 
  "EEManager": [
    [
      1652659203000, 
      166
    ]
  ], 
  "directADC": [
    [
      1652659203000, 
      95
    ]
  ], 
  "OVS": [
    [
      1652659203000, 
      29
    ]
  ], 
  "GyverOLED": [
    [
      1652659203000, 
      1077
    ]
  ], 
  "buildTime": [
    [
      1652659203000, 
      39
    ]
  ], 
  "GyverHTU21D": [
    [
      1652659203000, 
      186
    ]
  ], 
  "GRGB": [
    [
      1652659203000, 
      149
    ]
  ], 
  "GyverBME280": [
    [
      1652659203000, 
      224
    ]
  ], 
  "FFT_C": [
    [
      1652659203000, 
      87
    ]
  ], 
  "total": [
    [
      1652659203000, 
      15467
    ]
  ], 
  "GyverButton": [
    [
      1652659203000, 
      306
    ]
  ], 
  "GyverLibs-1": [], 
  "MicroUART": [
    [
      1652659203000, 
      33
    ]
  ], 
  "GyverTimer": [
    [
      1652659203000, 
      204
    ]
  ], 
  "FastBot": [
    [
      1652659203000, 
      1040
    ]
  ], 
  "GyverTransfer": [
    [
      1652659203000, 
      39
    ]
  ], 
  "EncButton": [
    [
      1652659203000, 
      1225
    ]
  ], 
  "cards_ui": [
    [
      1652659203000, 
      29
    ]
  ], 
  "mString": [
    [
      1652659203000, 
      72
    ]
  ], 
  "GyverMotor": [
    [
      1652659203000, 
      190
    ]
  ], 
  "GyverPID": [
    [
      1652659203000, 
      422
    ]
  ], 
  "AsyncStream": [
    [
      1652659203000, 
      98
    ]
  ], 
  "GyverRelay": [
    [
      1652659203000, 
      128
    ]
  ], 
  "Approxy": [
    [
      1652659203000, 
      54
    ]
  ], 
  "library-registry": [], 
  "BitPack": [
    [
      1652659203000, 
      40
    ]
  ], 
  "Hamming": [
    [
      1652659203000, 
      14
    ]
  ], 
  "SimplePortal": [
    [
      1652659203000, 
      132
    ]
  ], 
  "GyverHX711": [
    [
      1652659203000, 
      286
    ]
  ], 
  "GyverPower": [
    [
      1652659203000, 
      101
    ]
  ], 
  "Clap": [
    [
      1652659203000, 
      66
    ]
  ], 
  "GyverNTC": [
    [
      1652659203000, 
      231
    ]
  ], 
  "GyverLBUF": [], 
  "GyverLibs": [
    [
      1652659203000, 
      52
    ]
  ], 
  "microLED": [
    [
      1652659203000, 
      216
    ]
  ], 
  "GyverTimers": [
    [
      1652659203000, 
      233
    ]
  ], 
  "GyverDimmer": [
    [
      1652659203000, 
      93
    ]
  ], 
  "GyverPWM": [
    [
      1652659203000, 
      204
    ]
  ], 
  "Forecaster": [
    [
      1652659203000, 
      22
    ]
  ], 
  "GParser": [
    [
      1652659203000, 
      239
    ]
  ], 
  "GyverGFX": [
    [
      1652659203000, 
      60
    ]
  ], 
  "microWire": [
    [
      1652659203000, 
      72
    ]
  ], 
  "SoftServo": [
    [
      1652659203000, 
      40
    ]
  ], 
  "AccelMotor": [
    [
      1652659203000, 
      204
    ]
  ], 
  "GyverUART": [
    [
      1652659203000, 
      43
    ]
  ], 
  "gyverlibs.github.io": [], 
  "NecDecoder": [
    [
      1652659203000, 
      72
    ]
  ], 
  "GyverOS": [
    [
      1652659203000, 
      128
    ]
  ], 
  "QuickCharge": [
    [
      1652659203000, 
      111
    ]
  ], 
  "GyverMAX6675": [
    [
      1652659203000, 
      213
    ]
  ], 
  "microDS18B20": [
    [
      1652659203000, 
      380
    ]
  ], 
  "fixed": [
    [
      1652659203000, 
      34
    ]
  ], 
  "GyverFilters": [
    [
      1652659203000, 
      465
    ]
  ], 
  "TimerMs": [
    [
      1652659203000, 
      226
    ]
  ], 
  "Gyver433": [
    [
      1652659203000, 
      542
    ]
  ]
}