{
  "directTimers": [
    [
      1652480242, 
      73
    ]
  ], 
  "GyverStepper": [
    [
      1652480242, 
      954
    ]
  ], 
  "PWMrelay": [
    [
      1652480242, 
      131
    ]
  ], 
  "GyverEncoder": [
    [
      1652480242, 
      289
    ]
  ], 
  "CRT": [
    [
      1652480242, 
      18
    ]
  ], 
  "GyverPortal": [
    [
      1652480242, 
      2659
    ]
  ], 
  "GyverHC595": [
    [
      1652480242, 
      245
    ]
  ], 
  "UnixTime": [
    [
      1652480242, 
      407
    ]
  ], 
  "ServoSmooth": [
    [
      1652480242, 
      371
    ]
  ], 
  "GyverINA": [
    [
      1652480242, 
      313
    ]
  ], 
  "Psychrometer": [
    [
      1652480242, 
      52
    ]
  ], 
  "GyverMAX7219": [
    [
      1652480242, 
      427
    ]
  ], 
  "GyverWDT": [
    [
      1652480242, 
      155
    ]
  ], 
  "GyverBus": [
    [
      1652480242, 
      349
    ]
  ], 
  "Tachometer": [
    [
      1652480242, 
      272
    ]
  ], 
  "TimeRandom": [
    [
      1652480242, 
      31
    ]
  ], 
  "GyverTM1637": [
    [
      1652480242, 
      674
    ]
  ], 
  "AnalogKey": [
    [
      1652480242, 
      173
    ]
  ], 
  "VolAnalyzer": [
    [
      1652480242, 
      326
    ]
  ], 
  "microDS3231": [
    [
      1652480242, 
      623
    ]
  ], 
  "EasyHID": [
    [
      1652480242, 
      753
    ]
  ], 
  "GyverJoy": [
    [
      1652480242, 
      90
    ]
  ], 
  "Random16": [
    [
      1652480242, 
      127
    ]
  ], 
  "SevenSegmentsDisp": [
    [
      1652480242, 
      138
    ]
  ], 
  "GyverFIFO": [
    [
      1652480242, 
      58
    ]
  ], 
  "AlexGyver": [
    [
      1652480242, 
      5
    ]
  ], 
  "GyverNTP": [
    [
      1652480242, 
      453
    ]
  ], 
  "ProcessingPlotter": [
    [
      1652480242, 
      47
    ]
  ], 
  "EEManager": [
    [
      1652480242, 
      293
    ]
  ], 
  "directADC": [
    [
      1652480242, 
      310
    ]
  ], 
  "OVS": [
    [
      1652480242, 
      58
    ]
  ], 
  "GyverOLED": [
    [
      1652480242, 
      1914
    ]
  ], 
  "buildTime": [
    [
      1652480242, 
      75
    ]
  ], 
  "GyverHTU21D": [
    [
      1652480242, 
      232
    ]
  ], 
  "GRGB": [
    [
      1652480242, 
      257
    ]
  ], 
  "GyverBME280": [
    [
      1652480242, 
      369
    ]
  ], 
  "FFT_C": [
    [
      1652480242, 
      173
    ]
  ], 
  "total": [
    [
      1652480242, 
      29943
    ]
  ], 
  "gyverlibs.github.io": [
    [
      1652480242, 
      0
    ]
  ], 
  "GyverButton": [
    [
      1652480242, 
      559
    ]
  ], 
  "GyverLibs-1": [
    [
      1652480242, 
      0
    ]
  ], 
  "MicroUART": [
    [
      1652480242, 
      90
    ]
  ], 
  "GyverTimer": [
    [
      1652480242, 
      431
    ]
  ], 
  "FastBot": [
    [
      1652480242, 
      1687
    ]
  ], 
  "GyverTransfer": [
    [
      1652480242, 
      106
    ]
  ], 
  "EncButton": [
    [
      1652480242, 
      2790
    ]
  ], 
  "cards_ui": [
    [
      1652480242, 
      47
    ]
  ], 
  "mString": [
    [
      1652480242, 
      144
    ]
  ], 
  "GyverMotor": [
    [
      1652480242, 
      323
    ]
  ], 
  "GyverPID": [
    [
      1652480242, 
      641
    ]
  ], 
  "AsyncStream": [
    [
      1652480242, 
      194
    ]
  ], 
  "GyverRelay": [
    [
      1652480242, 
      171
    ]
  ], 
  "Approxy": [
    [
      1652480242, 
      80
    ]
  ], 
  "library-registry": [
    [
      1652480242, 
      1
    ]
  ], 
  "BitPack": [
    [
      1652480242, 
      54
    ]
  ], 
  "Hamming": [
    [
      1652480242, 
      23
    ]
  ], 
  "SimplePortal": [
    [
      1652480242, 
      291
    ]
  ], 
  "GyverHX711": [
    [
      1652480242, 
      434
    ]
  ], 
  "GyverPower": [
    [
      1652480242, 
      214
    ]
  ], 
  "Clap": [
    [
      1652480242, 
      184
    ]
  ], 
  "GyverNTC": [
    [
      1652480242, 
      541
    ]
  ], 
  "GyverLBUF": [
    [
      1652480242, 
      32
    ]
  ], 
  "GyverLibs": [
    [
      1652480242, 
      104
    ]
  ], 
  "microLED": [
    [
      1652480242, 
      543
    ]
  ], 
  "GyverTimers": [
    [
      1652480242, 
      417
    ]
  ], 
  "GyverDimmer": [
    [
      1652480242, 
      140
    ]
  ], 
  "GyverPWM": [
    [
      1652480242, 
      350
    ]
  ], 
  "Forecaster": [
    [
      1652480242, 
      43
    ]
  ], 
  "GParser": [
    [
      1652480242, 
      452
    ]
  ], 
  "GyverGFX": [
    [
      1652480242, 
      124
    ]
  ], 
  "microWire": [
    [
      1652480242, 
      149
    ]
  ], 
  "SoftServo": [
    [
      1652480242, 
      88
    ]
  ], 
  "AccelMotor": [
    [
      1652480242, 
      373
    ]
  ], 
  "GyverUART": [
    [
      1652480242, 
      139
    ]
  ], 
  "AlexGyver.github.io": [
    [
      1652480242, 
      3
    ]
  ], 
  "NecDecoder": [
    [
      1652480242, 
      149
    ]
  ], 
  "GyverOS": [
    [
      1652480242, 
      227
    ]
  ], 
  "QuickCharge": [
    [
      1652480242, 
      215
    ]
  ], 
  "GyverMAX6675": [
    [
      1652480242, 
      402
    ]
  ], 
  "microDS18B20": [
    [
      1652480242, 
      865
    ]
  ], 
  "fixed": [
    [
      1652480242, 
      48
    ]
  ], 
  "GyverFilters": [
    [
      1652480242, 
      621
    ]
  ], 
  "TimerMs": [
    [
      1652480242, 
      504
    ]
  ], 
  "Gyver433": [
    [
      1652480242, 
      1056
    ]
  ]
}